updatepkgs/__init__.py
updatepkgs/__main__.py
updatepkgs-1.0.2.dist-info/METADATA
updatepkgs-1.0.2.dist-info/WHEEL
updatepkgs-1.0.2.dist-info/entry_points.txt
updatepkgs-1.0.2.dist-info/top_level.txt
updatepkgs-1.0.2.dist-info/RECORD
