Metadata-Version: 2.4
Name: updatepkgs
Version: 1.0.2
Summary: A command-line tool for interactively updating and installing Python packages
Home-page: https://github.com/dnettz/updatepkgs
Author: Dishani William
Author-email: Dishani William <dishaniwilliam@outlook.com>
License: MIT
Keywords: pip,package,update,installer,search,cli
Classifier: Development Status :: 4 - Beta
Classifier: Intended Audience :: Developers
Classifier: License :: OSI Approved :: MIT License
Classifier: Operating System :: OS Independent
Classifier: Programming Language :: Python
Classifier: Programming Language :: Python :: 3
Classifier: Programming Language :: Python :: 3.7
Classifier: Topic :: Software Development :: Build Tools
Classifier: Environment :: Console
Requires-Python: >=3.7
Requires-Dist: pip
Requires-Dist: requests
Requires-Dist: rich
Requires-Dist: tqdm
Requires-Dist: setuptools
Dynamic: author
Dynamic: home-page
Dynamic: requires-python
